rtl/data_mem.v
`default_nettype none

module data_memory(
    input clk,
    input memRead, memWrite,
    input [31:0] ALU_result, rs2_val,
    output reg [31:0] mem_result
);

    reg [31:0] memory [0:1023];

    integer i;
    initial begin
        for (i = 0; i < 1024; i = i + 1)
            memory[i] = 32'h0;
    end

    always @(posedge clk) begin
        if (memWrite)
            memory[ALU_result >> 2] <= rs2_val;
    end

    always @(*) begin
        if (memRead)
            mem_result = memory[ALU_result >> 2];
        else
            mem_result = 32'h0;
    end

endmodule

data_mem_tb.v
`timescale 1ns/1ps
`default_nettype none

module data_mem_tb;

    reg clk;
    reg memRead, memWrite;
    reg [31:0] ALU_result, rs2_val;
    wire [31:0] mem_result;

    data_memory uut(
        .clk(clk),
        .memRead(memRead), .memWrite(memWrite),
        .ALU_result(ALU_result), .rs2_val(rs2_val),
        .mem_result(mem_result)
    );

    always #5 clk = ~clk;

    initial begin
        $dumpfile("data_mem_tb.vcd");
        $dumpvars(0, data_mem_tb);

        clk = 0;
        memRead = 0; memWrite = 0;
        ALU_result = 0; rs2_val = 0;

        // 1. write 42 to address 0
        @(negedge clk);
        memWrite  = 1;
        ALU_result = 32'h00000000;
        rs2_val   = 32'd42;
        @(posedge clk); #1;
        memWrite  = 0;
        $display("Write 42 to addr 0 done");

        // 2. read back from address 0
        memRead   = 1;
        ALU_result = 32'h00000000;
        #1;
        $display("Read addr 0  -> %d (expected 42)", mem_result);
        memRead = 0;

        // 3. write 99 to address 4
        @(negedge clk);
        memWrite  = 1;
        ALU_result = 32'h00000004;
        rs2_val   = 32'd99;
        @(posedge clk); #1;
        memWrite  = 0;
        $display("Write 99 to addr 4 done");

        // 4. read back from address 4
        memRead   = 1;
        ALU_result = 32'h00000004;
        #1;
        $display("Read addr 4  -> %d (expected 99)", mem_result);
        memRead = 0;

        // 5. read address that was never written
        memRead   = 1;
        ALU_result = 32'h00000008;
        #1;
        $display("Read addr 8  -> %d (expected 0)", mem_result);
        memRead = 0;

        // 6. no read no write -> result should be 0 
        memRead = 0; memWrite = 0;
        ALU_result = 32'h00000000;
        #1;
        $display("No op addr 0 -> %d (expected 0)", mem_result);

        $display("data_mem tests done.");
        $finish;
    end

endmodule

data_mem_tb.vcd
$date
	Mon Apr 20 18:52:06 2026
$end
$version
	Icarus Verilog
$end
$timescale
	1ps
$end
$scope module data_mem_tb $end
$var wire 32 ! mem_result [31:0] $end
$var reg 32 " ALU_result [31:0] $end
$var reg 1 # clk $end
$var reg 1 $ memRead $end
$var reg 1 % memWrite $end
$var reg 32 & rs2_val [31:0] $end
$scope module uut $end
$var wire 32 ' ALU_result [31:0] $end
$var wire 1 # clk $end
$var wire 1 $ memRead $end
$var wire 1 % memWrite $end
$var wire 32 ( rs2_val [31:0] $end
$var reg 32 ) mem_result [31:0] $end
$var integer 32 * i [31:0] $end
$upscope $end
$upscope $end
$enddefinitions $end
$comment Show the parameter values. $end
$dumpall
$end
#0
$dumpvars
b10000000000 *
b0 )
b0 (
b0 '
b0 &
0%
0$
0#
b0 "
b0 !
$end
#5000
1#
#10000
b101010 &
b101010 (
1%
0#
#15000
1#
#16000
b101010 !
b101010 )
1$
0%
#17000
b0 !
b0 )
0$
#20000
b1100011 &
b1100011 (
b100 "
b100 '
1%
0#
#25000
1#
#26000
b1100011 !
b1100011 )
1$
0%
#27000
b0 !
b0 )
b1000 "
b1000 '
1$
#28000
b0 "
b0 '
0$
