mem_stage.v
`default_nettype none

module MEM_WB(
    input clk,
    input rst,

    input [31:0] ALU_result_r,
    input [31:0] mem_result_r,
    input [31:0] PC_plus_4_r,
    input [1:0]  resultSrc_r,
    input        regWrite_r,
    input [4:0]  rd_r,

    output reg [31:0] ALU_result,
    output reg [31:0] mem_result,
    output reg [31:0] PC_plus_4,
    output reg [1:0]  resultSrc,
    output reg        regWrite,
    output reg [4:0]  rd
);

    always @(posedge clk or posedge rst) begin
        if (rst) begin
            ALU_result <= 32'b0;
            mem_result  <= 32'b0;
            PC_plus_4   <= 32'b0;
            resultSrc   <= 2'b0;
            regWrite    <= 1'b0;
            rd          <= 5'b0;
        end else begin
            ALU_result <= ALU_result_r;
            mem_result  <= mem_result_r;
            PC_plus_4   <= PC_plus_4_r;
            resultSrc   <= resultSrc_r;
            regWrite    <= regWrite_r;
            rd          <= rd_r;
        end
    end

endmodule


module mem_stage(
    input clk,
    input rst,

    input memRead_in,
    input memWrite_in,
    input regWrite_in,
    input [1:0] resultSrc_in,
    input [4:0] rd_in,

    input [31:0] ALU_result_in,
    input [31:0] rs2_val_in,
    input [31:0] PC_in,

    output [31:0] ALU_result_out,
    output [31:0] mem_result_out,
    output [31:0] PC_plus_4_out,
    output [1:0]  resultSrc_out,
    output        regWrite_out,
    output [4:0]  rd_out
);

    wire [31:0] mem_result_w;
    wire [31:0] PC_plus_4_w;

    assign PC_plus_4_w = PC_in + 32'd4;

    data_memory DMEM (
        .clk(clk),
        .memRead(memRead_in),
        .memWrite(memWrite_in),
        .ALU_result(ALU_result_in),
        .rs2_val(rs2_val_in),
        .mem_result(mem_result_w)
    );

    MEM_WB pipe_reg (
        .clk(clk),
        .rst(rst),
        .ALU_result_r(ALU_result_in),
        .mem_result_r(mem_result_w),
        .PC_plus_4_r(PC_plus_4_w),
        .resultSrc_r(resultSrc_in),
        .regWrite_r(regWrite_in),
        .rd_r(rd_in),

        .ALU_result(ALU_result_out),
        .mem_result(mem_result_out),
        .PC_plus_4(PC_plus_4_out),
        .resultSrc(resultSrc_out),
        .regWrite(regWrite_out),
        .rd(rd_out)
    );

endmodule

rtl/data_mem.v
`default_nettype none

module data_memory(
    input clk,
    input memRead, memWrite,
    input [31:0] ALU_result, rs2_val,
    output reg [31:0] mem_result
);

    reg [31:0] memory [0:1023];

    integer i;
    initial begin
        for (i = 0; i < 1024; i = i + 1)
            memory[i] = 32'h0;
    end

    always @(posedge clk) begin
        if (memWrite)
            memory[ALU_result >> 2] <= rs2_val;
    end

    always @(*) begin
        if (memRead)
            mem_result = memory[ALU_result >> 2];
        else
            mem_result = 32'h0;
    end

endmodule

tb/MEM_tb.v
`timescale 1ns/1ps
`default_nettype none

module MEM_tb;

    reg clk, rst;
    reg memRead_in, memWrite_in, regWrite_in;
    reg [1:0] resultSrc_in;
    reg [4:0] rd_in;
    reg [31:0] ALU_result_in, rs2_val_in, PC_in;

    wire [31:0] ALU_result_out, mem_result_out, PC_plus_4_out;
    wire [1:0] resultSrc_out;
    wire regWrite_out;
    wire [4:0] rd_out;

    mem_stage uut (
        .clk(clk),
        .rst(rst),
        .memRead_in(memRead_in),
        .memWrite_in(memWrite_in),
        .regWrite_in(regWrite_in),
        .resultSrc_in(resultSrc_in),
        .rd_in(rd_in),
        .ALU_result_in(ALU_result_in),
        .rs2_val_in(rs2_val_in),
        .PC_in(PC_in),
        .ALU_result_out(ALU_result_out),
        .mem_result_out(mem_result_out),
        .PC_plus_4_out(PC_plus_4_out),
        .resultSrc_out(resultSrc_out),
        .regWrite_out(regWrite_out),
        .rd_out(rd_out)
    );

    always #5 clk = ~clk;

    initial begin
        $dumpfile("MEM_tb.vcd");
        $dumpvars(0, MEM_tb);

        clk = 0;
        rst = 1;

        memRead_in = 0;
        memWrite_in = 0;
        regWrite_in = 0;
        resultSrc_in = 2'b00;
        rd_in = 5'b0;
        ALU_result_in = 32'b0;
        rs2_val_in = 32'b0;
        PC_in = 32'b0;

        #12 rst = 0;

        @(negedge clk);
        memWrite_in = 1;
        memRead_in = 0;
        regWrite_in = 0;
        resultSrc_in = 2'b00;
        ALU_result_in = 32'h0000_0000;
        rs2_val_in = 32'd55;
        PC_in = 32'h0000_0100;
        rd_in = 5'd1;

        @(posedge clk);
        #1;
        memWrite_in = 0;
        $display("MEM write done | stored %d at addr 0", rs2_val_in);

        @(negedge clk);
        memRead_in = 1;
        memWrite_in = 0;
        regWrite_in = 1;
        resultSrc_in = 2'b01;
        ALU_result_in = 32'h0000_0000;
        rs2_val_in = 32'd0;
        PC_in = 32'h0000_0100;
        rd_in = 5'd2;

        @(posedge clk);
        #1;
        $display("MEM read  | mem_result_out = %d (expected 55)", mem_result_out);
        $display("PIPE OUT  | ALU=%h MEM=%h PC+4=%h resultSrc=%b regWrite=%b rd=%0d",
                 ALU_result_out, mem_result_out, PC_plus_4_out, resultSrc_out, regWrite_out, rd_out);

        @(negedge clk);
        memRead_in = 0;
        memWrite_in = 0;
        regWrite_in = 1;
        resultSrc_in = 2'b10;
        ALU_result_in = 32'h1234_5678;
        rs2_val_in = 32'h0;
        PC_in = 32'h0000_0200;
        rd_in = 5'd3;

        @(posedge clk);
        #1;
        $display("PC+4 test | PC_plus_4_out = %h (expected 00000204)", PC_plus_4_out);

        $display("MEM_tb done.");
        $finish;
    end

endmodule

logs/MEM_tb.vcd
$date
	Mon Apr 20 18:54:10 2026
$end
$version
	Icarus Verilog
$end
$timescale
	1ps
$end
$scope module MEM_tb $end
$var wire 2 ! resultSrc_out [1:0] $end
$var wire 1 " regWrite_out $end
$var wire 5 # rd_out [4:0] $end
$var wire 32 $ mem_result_out [31:0] $end
$var wire 32 % PC_plus_4_out [31:0] $end
$var wire 32 & ALU_result_out [31:0] $end
$var reg 32 ' ALU_result_in [31:0] $end
$var reg 32 ( PC_in [31:0] $end
$var reg 1 ) clk $end
$var reg 1 * memRead_in $end
$var reg 1 + memWrite_in $end
$var reg 5 , rd_in [4:0] $end
$var reg 1 - regWrite_in $end
$var reg 2 . resultSrc_in [1:0] $end
$var reg 32 / rs2_val_in [31:0] $end
$var reg 1 0 rst $end
$scope module uut $end
$var wire 32 1 ALU_result_in [31:0] $end
$var wire 32 2 PC_in [31:0] $end
$var wire 1 ) clk $end
$var wire 1 * memRead_in $end
$var wire 1 + memWrite_in $end
$var wire 5 3 rd_in [4:0] $end
$var wire 1 - regWrite_in $end
$var wire 2 4 resultSrc_in [1:0] $end
$var wire 32 5 rs2_val_in [31:0] $end
$var wire 1 0 rst $end
$var wire 2 6 resultSrc_out [1:0] $end
$var wire 1 " regWrite_out $end
$var wire 5 7 rd_out [4:0] $end
$var wire 32 8 mem_result_w [31:0] $end
$var wire 32 9 mem_result_out [31:0] $end
$var wire 32 : PC_plus_4_w [31:0] $end
$var wire 32 ; PC_plus_4_out [31:0] $end
$var wire 32 < ALU_result_out [31:0] $end
$scope module DMEM $end
$var wire 32 = ALU_result [31:0] $end
$var wire 1 ) clk $end
$var wire 1 * memRead $end
$var wire 1 + memWrite $end
$var wire 32 > rs2_val [31:0] $end
$var reg 32 ? mem_result [31:0] $end
$var integer 32 @ i [31:0] $end
$upscope $end
$scope module pipe_reg $end
$var wire 32 A ALU_result_r [31:0] $end
$var wire 32 B PC_plus_4_r [31:0] $end
$var wire 1 ) clk $end
$var wire 32 C mem_result_r [31:0] $end
$var wire 5 D rd_r [4:0] $end
$var wire 1 - regWrite_r $end
$var wire 2 E resultSrc_r [1:0] $end
$var wire 1 0 rst $end
$var reg 32 F ALU_result [31:0] $end
$var reg 32 G PC_plus_4 [31:0] $end
$var reg 32 H mem_result [31:0] $end
$var reg 5 I rd [4:0] $end
$var reg 1 " regWrite $end
$var reg 2 J resultSrc [1:0] $end
$upscope $end
$upscope $end
$upscope $end
$enddefinitions $end
$comment Show the parameter values. $end
$dumpall
$end
#0
$dumpvars
b0 J
b0 I
b0 H
b0 G
b0 F
b0 E
b0 D
b0 C
b100 B
b0 A
b10000000000 @
b0 ?
b0 >
b0 =
b0 <
b0 ;
b100 :
b0 9
b0 8
b0 7
b0 6
b0 5
b0 4
b0 3
b0 2
b0 1
10
b0 /
b0 .
0-
b0 ,
0+
0*
0)
b0 (
b0 '
b0 &
b0 %
b0 $
b0 #
0"
b0 !
$end
#5000
1)
#10000
0)
#12000
00
#15000
b100 %
b100 ;
b100 G
1)
#20000
b1 ,
b1 3
b1 D
b100000100 :
b100000100 B
b100000000 (
b100000000 2
b110111 /
b110111 5
b110111 >
1+
0)
#25000
b1 #
b1 7
b1 I
b100000100 %
b100000100 ;
b100000100 G
1)
#26000
0+
#30000
b110111 8
b110111 ?
b110111 C
b10 ,
b10 3
b10 D
b0 /
b0 5
b0 >
b1 .
b1 4
b1 E
1-
1*
0)
#35000
b10 #
b10 7
b10 I
1"
b1 !
b1 6
b1 J
b110111 $
b110111 9
b110111 H
1)
#40000
b0 8
b0 ?
b0 C
b11 ,
b11 3
b11 D
b1000000100 :
b1000000100 B
b1000000000 (
b1000000000 2
b10010001101000101011001111000 '
b10010001101000101011001111000 1
b10010001101000101011001111000 =
b10010001101000101011001111000 A
b10 .
b10 4
b10 E
0*
0)
#45000
b11 #
b11 7
b11 I
b10 !
b10 6
b10 J
b1000000100 %
b1000000100 ;
b1000000100 G
b0 $
b0 9
b0 H
b10010001101000101011001111000 &
b10010001101000101011001111000 <
b10010001101000101011001111000 F
1)
